sphinx_paragraph_extractor/__init__.py
sphinx_paragraph_extractor-1.0.4.dist-info/LICENSE.txt
sphinx_paragraph_extractor-1.0.4.dist-info/METADATA
sphinx_paragraph_extractor-1.0.4.dist-info/WHEEL
sphinx_paragraph_extractor-1.0.4.dist-info/entry_points.txt
sphinx_paragraph_extractor-1.0.4.dist-info/top_level.txt
sphinx_paragraph_extractor-1.0.4.dist-info/RECORD
