Metadata-Version: 2.1
Name: sphinx-paragraph-extractor
Version: 1.0.4
Summary: A builder for Sphinx to extract paragraphs from docs.
Home-page: https://github.com/mitsuse/sphinx-paragraph-extractor
Author: Tomoya Kose
Author-email: tomoya@mitsuse.jp
License: MIT
Platform: UNKNOWN
Classifier: License :: OSI Approved :: MIT License
Classifier: Programming Language :: Python :: 3.6
Classifier: Programming Language :: Python :: 3.7
Requires-Dist: sphinx (>=2.0.1<3.0.0)
